pylapi/__init__.py
pylapi/__version__.py
pylapi/autogen.py
pylapi/autogen_template.py
pylapi/config.py
pylapi/pylapi.py
pylapi-0.12.16.dist-info/LICENSE
pylapi-0.12.16.dist-info/METADATA
pylapi-0.12.16.dist-info/WHEEL
pylapi-0.12.16.dist-info/entry_points.txt
pylapi-0.12.16.dist-info/top_level.txt
pylapi-0.12.16.dist-info/RECORD
