Metadata-Version: 2.1
Name: pylapi
Version: 0.12.16
Summary: Python Lightweight API (PyLapi)
Home-page: https://github.com/jackyko8/pylapi
Author: Jacky Ko
Author-email: 
License: MIT
Project-URL: Changelog, https://github.com/jackyko8/pylapi/blob/main/RELEASE.md
Project-URL: Code, https://github.com/jackyko8/pylapi
Project-URL: Download, https://pypi.org/project/pylapi/
Project-URL: Homepage, https://www.pylapi.org/
Project-URL: Issue tracker, https://github.com/jackyko8/pylapi/issues
Classifier: Programming Language :: Python :: 3
Classifier: License :: OSI Approved :: MIT License
Classifier: Operating System :: OS Independent
Requires-Python: >=3.7
License-File: LICENSE
Requires-Dist: magico >=1.0
Requires-Dist: urllib3 <1.27,>=1.21.1
Requires-Dist: requests >=2.5
Requires-Dist: PyYAML >=5.1
